pysisl/__init__.py
pysisl/deep_merger.py
pysisl/explode_structure.py
pysisl/parser_error.py
pysisl/parsetab.py
pysisl/remove_data.py
pysisl/sisl_decoder.py
pysisl/sisl_encoder.py
pysisl/sisl_joiner.py
pysisl/sisl_lexer.py
pysisl/sisl_parser.py
pysisl/sisl_splitter.py
pysisl/sisl_type_flatten.py
pysisl/sisl_wrapper.py
tests/__init__.py
tests/test_deep_merger.py
tests/test_explode_structure.py
tests/test_remove_data.py
tests/test_sisl_decoder.py
tests/test_sisl_decoder_raw_types.py
tests/test_sisl_encoder.py
tests/test_sisl_encoder_decoder.py
tests/test_sisl_joiner.py
tests/test_sisl_splitter.py
tests/test_sisl_type_flatten.py
tests/test_sisl_wrapper.py
tests_random_abnf/__init__.py
tests_random_abnf/random_abnf_tests.py
pysisl-0.0.13.dist-info/LICENSE
pysisl-0.0.13.dist-info/METADATA
pysisl-0.0.13.dist-info/WHEEL
pysisl-0.0.13.dist-info/top_level.txt
pysisl-0.0.13.dist-info/RECORD
