Metadata-Version: 2.1
Name: pysisl
Version: 0.0.13
Summary: A python library for serialising and deserialising SISL (Simple Information Serialization Language)
Home-page: https://oakdoor.io
Author: Oakdoor
Author-email: info@oakdoor.io
License: UNKNOWN
Project-URL: Project, https://oakdoor.io
Platform: UNKNOWN
Classifier: Programming Language :: Python :: 3
Classifier: License :: OSI Approved :: MIT License
Classifier: Operating System :: OS Independent
Requires-Python: >=3.6
License-File: LICENSE
Requires-Dist: ply
Requires-Dist: jsonschema
Requires-Dist: deepmerge
Requires-Dist: mergedeep
Requires-Dist: construct
